[
    {
        "key": "dbln",
        "value": "%7B%2261571739812484%22%3A%22A7jw0fTa%22%7D",
        "domain": "facebook.com",
        "path": "/login/device-based/",
        "hostOnly": false,
        "creation": "2025-05-22T11:19:06.214Z",
        "lastAccessed": "2025-05-22T11:19:06.214Z"
    },
    {
        "key": "datr",
        "value": "-rAuaB0kkW-k_obcPYzAhEol",
        "domain": "facebook.com",
        "path": "/",
        "hostOnly": false,
        "creation": "2025-05-22T11:19:06.214Z",
        "lastAccessed": "2025-05-22T11:19:06.214Z"
    },
    {
        "key": "sb",
        "value": "-rAuaLKsydCvA58_W83usr97",
        "domain": "facebook.com",
        "path": "/",
        "hostOnly": false,
        "creation": "2025-05-22T11:19:06.214Z",
        "lastAccessed": "2025-05-22T11:19:06.214Z"
    },
    {
        "key": "ps_l",
        "value": "1",
        "domain": "facebook.com",
        "path": "/",
        "hostOnly": false,
        "creation": "2025-05-22T11:19:06.214Z",
        "lastAccessed": "2025-05-22T11:19:06.214Z"
    },
    {
        "key": "ps_n",
        "value": "1",
        "domain": "facebook.com",
        "path": "/",
        "hostOnly": false,
        "creation": "2025-05-22T11:19:06.214Z",
        "lastAccessed": "2025-05-22T11:19:06.214Z"
    },
    {
        "key": "m_pixel_ratio",
        "value": "2.75",
        "domain": "facebook.com",
        "path": "/",
        "hostOnly": false,
        "creation": "2025-05-22T11:19:06.214Z",
        "lastAccessed": "2025-05-22T11:19:06.214Z"
    },
    {
        "key": "wd",
        "value": "393x876",
        "domain": "facebook.com",
        "path": "/",
        "hostOnly": false,
        "creation": "2025-05-22T11:19:06.214Z",
        "lastAccessed": "2025-05-22T11:19:06.214Z"
    },
    {
        "key": "locale",
        "value": "en_GB",
        "domain": "facebook.com",
        "path": "/",
        "hostOnly": false,
        "creation": "2025-05-22T11:19:06.214Z",
        "lastAccessed": "2025-05-22T11:19:06.215Z"
    },
    {
        "key": "vpd",
        "value": "v1%3B746x393x2.75",
        "domain": "facebook.com",
        "path": "/",
        "hostOnly": false,
        "creation": "2025-05-22T11:19:06.215Z",
        "lastAccessed": "2025-05-22T11:19:06.215Z"
    },
    {
        "key": "x-referer",
        "value": "eyJyIjoiL2hvbWUucGhwIiwiaCI6Ii9ob21lLnBocCIsInMiOiJtIn0%3D",
        "domain": "facebook.com",
        "path": "/",
        "hostOnly": false,
        "creation": "2025-05-22T11:19:06.215Z",
        "lastAccessed": "2025-05-22T11:19:06.215Z"
    },
    {
        "key": "c_user",
        "value": "61571739812484",
        "domain": "facebook.com",
        "path": "/",
        "hostOnly": false,
        "creation": "2025-05-22T11:19:06.215Z",
        "lastAccessed": "2025-05-22T11:19:06.215Z"
    },
    {
        "key": "fr",
        "value": "0SsSteGpVpKKKoGOk.AWdP436cwWaKzBNIpJTEtioCZeirBEC-XwZ44dbjszNdRkq81-E.BoLrD6..AAA.0.0.BoLwgk.AWfrVTKIugXIvKATCfmjGq-FxIA",
        "domain": "facebook.com",
        "path": "/",
        "hostOnly": false,
        "creation": "2025-05-22T11:19:06.215Z",
        "lastAccessed": "2025-05-22T11:19:06.215Z"
    },
    {
        "key": "xs",
        "value": "27%3AChQW8D04HfjjHg%3A2%3A1747912740%3A-1%3A4130",
        "domain": "facebook.com",
        "path": "/",
        "hostOnly": false,
        "creation": "2025-05-22T11:19:06.215Z",
        "lastAccessed": "2025-05-22T11:19:06.215Z"
    },
    {
        "key": "fbl_st",
        "value": "101036503%3BT%3A29131879",
        "domain": "facebook.com",
        "path": "/",
        "hostOnly": false,
        "creation": "2025-05-22T11:19:06.215Z",
        "lastAccessed": "2025-05-22T11:19:06.215Z"
    },
    {
        "key": "wl_cbv",
        "value": "v2%3Bclient_version%3A2824%3Btimestamp%3A1747912743",
        "domain": "facebook.com",
        "path": "/",
        "hostOnly": false,
        "creation": "2025-05-22T11:19:06.215Z",
        "lastAccessed": "2025-05-22T11:19:06.215Z"
    }
]
