[
    {
        "key": "datr",
        "value": "lcj_ZiP3y0iUk5w1tDwZswIC",
        "domain": "facebook.com",
        "path": "/",
        "hostOnly": false,
        "creation": "2024-10-29T08:35:17.657Z",
        "lastAccessed": "2024-10-29T08:35:17.658Z"
    },
    {
        "key": "sb",
        "value": "lcj_ZpPXDyoW7VmZV-GcUyRD",
        "domain": "facebook.com",
        "path": "/",
        "hostOnly": false,
        "creation": "2024-10-29T08:35:17.658Z",
        "lastAccessed": "2024-10-29T08:35:17.658Z"
    },
    {
        "key": "vpd",
        "value": "v1%3B746x393x2.75",
        "domain": "facebook.com",
        "path": "/",
        "hostOnly": false,
        "creation": "2024-10-29T08:35:17.658Z",
        "lastAccessed": "2024-10-29T08:35:17.658Z"
    },
    {
        "key": "ps_l",
        "value": "1",
        "domain": "facebook.com",
        "path": "/",
        "hostOnly": false,
        "creation": "2024-10-29T08:35:17.658Z",
        "lastAccessed": "2024-10-29T08:35:17.658Z"
    },
    {
        "key": "ps_n",
        "value": "1",
        "domain": "facebook.com",
        "path": "/",
        "hostOnly": false,
        "creation": "2024-10-29T08:35:17.658Z",
        "lastAccessed": "2024-10-29T08:35:17.658Z"
    },
    {
        "key": "locale",
        "value": "en_GB",
        "domain": "facebook.com",
        "path": "/",
        "hostOnly": false,
        "creation": "2024-10-29T08:35:17.658Z",
        "lastAccessed": "2024-10-29T08:35:17.658Z"
    },
    {
        "key": "m_pixel_ratio",
        "value": "2.75",
        "domain": "facebook.com",
        "path": "/",
        "hostOnly": false,
        "creation": "2024-10-29T08:35:17.658Z",
        "lastAccessed": "2024-10-29T08:35:17.658Z"
    },
    {
        "key": "wd",
        "value": "393x746",
        "domain": "facebook.com",
        "path": "/",
        "hostOnly": false,
        "creation": "2024-10-29T08:35:17.658Z",
        "lastAccessed": "2024-10-29T08:35:17.658Z"
    },
    {
        "key": "c_user",
        "value": "100001256303783",
        "domain": "facebook.com",
        "path": "/",
        "hostOnly": false,
        "creation": "2024-10-29T08:35:17.658Z",
        "lastAccessed": "2024-10-29T08:35:17.658Z"
    },
    {
        "key": "fr",
        "value": "0us5YQCmd4lqPc4nF.AWXgDcl2vnvx7PHnMEoiP4biwLg.Bm_8iV..AAA.0.0.BnIJ4o.AWVqSGLAL_k",
        "domain": "facebook.com",
        "path": "/",
        "hostOnly": false,
        "creation": "2024-10-29T08:35:17.658Z",
        "lastAccessed": "2024-10-29T08:35:17.658Z"
    },
    {
        "key": "xs",
        "value": "40%3AI0e0qfV4GBPzhw%3A2%3A1730190888%3A-1%3A4130",
        "domain": "facebook.com",
        "path": "/",
        "hostOnly": false,
        "creation": "2024-10-29T08:35:17.658Z",
        "lastAccessed": "2024-10-29T08:35:17.658Z"
    },
    {
        "key": "fbl_st",
        "value": "100722918%3BT%3A28836514",
        "domain": "facebook.com",
        "path": "/",
        "hostOnly": false,
        "creation": "2024-10-29T08:35:17.658Z",
        "lastAccessed": "2024-10-29T08:35:17.658Z"
    },
    {
        "key": "wl_cbv",
        "value": "v2%3Bclient_version%3A2656%3Btimestamp%3A1730190890",
        "domain": "facebook.com",
        "path": "/",
        "hostOnly": false,
        "creation": "2024-10-29T08:35:17.658Z",
        "lastAccessed": "2024-10-29T08:35:17.658Z"
    }
]